{"Objective":1365.0,"EdgesResult":[{"Source":"S1","Destination":"N1","Commodity":"S1T2k2","Value":1.0},{"Source":"S1","Destination":"N3","Commodity":"S1T2k2","Value":0.0},{"Source":"S2","Destination":"N2","Commodity":"S1T2k2","Value":0.0},{"Source":"S2","Destination":"N4","Commodity":"S1T2k2","Value":0.0},{"Source":"S3","Destination":"N3","Commodity":"S1T2k2","Value":0.0},{"Source":"S3","Destination":"N5","Commodity":"S1T2k2","Value":0.0},{"Source":"N1","Destination":"N2","Commodity":"S1T2k2","Value":0.0},{"Source":"N1","Destination":"N6","Commodity":"S1T2k2","Value":1.0},{"Source":"N2","Destination":"N1","Commodity":"S1T2k2","Value":0.0},{"Source":"N2","Destination":"N3","Commodity":"S1T2k2","Value":0.0},{"Source":"N2","Destination":"N5","Commodity":"S1T2k2","Value":0.0},{"Source":"N2","Destination":"N6","Commodity":"S1T2k2","Value":0.0},{"Source":"N2","Destination":"N7","Commodity":"S1T2k2","Value":0.0},{"Source":"N3","Destination":"N2","Commodity":"S1T2k2","Value":0.0},{"Source":"N3","Destination":"N4","Commodity":"S1T2k2","Value":0.0},{"Source":"N3","Destination":"N5","Commodity":"S1T2k2","Value":0.0},{"Source":"N3","Destination":"N7","Commodity":"S1T2k2","Value":0.0},{"Source":"N4","Destination":"N3","Commodity":"S1T2k2","Value":0.0},{"Source":"N4","Destination":"N5","Commodity":"S1T2k2","Value":0.0},{"Source":"N5","Destination":"N2","Commodity":"S1T2k2","Value":0.0},{"Source":"N5","Destination":"N3","Commodity":"S1T2k2","Value":0.0},{"Source":"N5","Destination":"N4","Commodity":"S1T2k2","Value":0.0},{"Source":"N5","Destination":"N6","Commodity":"S1T2k2","Value":0.0},{"Source":"N5","Destination":"N7","Commodity":"S1T2k2","Value":0.0},{"Source":"N5","Destination":"N8","Commodity":"S1T2k2","Value":0.0},{"Source":"N6","Destination":"N1","Commodity":"S1T2k2","Value":0.0},{"Source":"N6","Destination":"N2","Commodity":"S1T2k2","Value":0.0},{"Source":"N6","Destination":"N5","Commodity":"S1T2k2","Value":0.0},{"Source":"N6","Destination":"N7","Commodity":"S1T2k2","Value":0.0},{"Source":"N7","Destination":"N2","Commodity":"S1T2k2","Value":0.0},{"Source":"N7","Destination":"N3","Commodity":"S1T2k2","Value":0.0},{"Source":"N7","Destination":"N5","Commodity":"S1T2k2","Value":0.0},{"Source":"N7","Destination":"N6","Commodity":"S1T2k2","Value":0.0},{"Source":"N7","Destination":"N8","Commodity":"S1T2k2","Value":0.0},{"Source":"N8","Destination":"N5","Commodity":"S1T2k2","Value":0.0},{"Source":"N8","Destination":"N7","Commodity":"S1T2k2","Value":0.0},{"Source":"T1","Destination":"T1k1","Commodity":"S1T2k2","Value":0.0},{"Source":"S1","Destination":"T1k1","Commodity":"S1T2k2","Value":0.0},{"Source":"T2","Destination":"T2k2","Commodity":"S1T2k2","Value":1.0},{"Source":"S1","Destination":"T2k2","Commodity":"S1T2k2","Value":0.0},{"Source":"T2","Destination":"T2k3","Commodity":"S1T2k2","Value":0.0},{"Source":"S2","Destination":"T2k3","Commodity":"S1T2k2","Value":0.0},{"Source":"T1","Destination":"T1k4","Commodity":"S1T2k2","Value":0.0},{"Source":"S2","Destination":"T1k4","Commodity":"S1T2k2","Value":0.0},{"Source":"N6","Destination":"T2","Commodity":"S1T2k2","Value":1.0},{"Source":"N7","Destination":"T2","Commodity":"S1T2k2","Value":0.0},{"Source":"N8","Destination":"T2","Commodity":"S1T2k2","Value":0.0},{"Source":"T2","Destination":"T2k4","Commodity":"S1T2k2","Value":0.0},{"Source":"S2","Destination":"T2k4","Commodity":"S1T2k2","Value":0.0},{"Source":"T3","Destination":"T3k4","Commodity":"S1T2k2","Value":0.0},{"Source":"S2","Destination":"T3k4","Commodity":"S1T2k2","Value":0.0},{"Source":"T3","Destination":"T3k5","Commodity":"S1T2k2","Value":0.0},{"Source":"S3","Destination":"T3k5","Commodity":"S1T2k2","Value":0.0},{"Source":"N6","Destination":"T1","Commodity":"S1T2k2","Value":0.0},{"Source":"N7","Destination":"T1","Commodity":"S1T2k2","Value":0.0},{"Source":"T1","Destination":"T1k6","Commodity":"S1T2k2","Value":0.0},{"Source":"S3","Destination":"T1k6","Commodity":"S1T2k2","Value":0.0},{"Source":"N5","Destination":"T3","Commodity":"S1T2k2","Value":0.0},{"Source":"N8","Destination":"T3","Commodity":"S1T2k2","Value":0.0},{"Source":"T3","Destination":"T3k6","Commodity":"S1T2k2","Value":0.0},{"Source":"S3","Destination":"T3k6","Commodity":"S1T2k2","Value":0.0},{"Source":"S1","Destination":"N1","Commodity":"S2T2k3","Value":0.0},{"Source":"S1","Destination":"N3","Commodity":"S2T2k3","Value":0.0},{"Source":"S2","Destination":"N2","Commodity":"S2T2k3","Value":1.0},{"Source":"S2","Destination":"N4","Commodity":"S2T2k3","Value":0.0},{"Source":"S3","Destination":"N3","Commodity":"S2T2k3","Value":0.0},{"Source":"S3","Destination":"N5","Commodity":"S2T2k3","Value":0.0},{"Source":"N1","Destination":"N2","Commodity":"S2T2k3","Value":0.0},{"Source":"N1","Destination":"N6","Commodity":"S2T2k3","Value":0.0},{"Source":"N2","Destination":"N1","Commodity":"S2T2k3","Value":0.0},{"Source":"N2","Destination":"N3","Commodity":"S2T2k3","Value":0.0},{"Source":"N2","Destination":"N5","Commodity":"S2T2k3","Value":0.0},{"Source":"N2","Destination":"N6","Commodity":"S2T2k3","Value":0.0},{"Source":"N2","Destination":"N7","Commodity":"S2T2k3","Value":1.0},{"Source":"N3","Destination":"N2","Commodity":"S2T2k3","Value":0.0},{"Source":"N3","Destination":"N4","Commodity":"S2T2k3","Value":0.0},{"Source":"N3","Destination":"N5","Commodity":"S2T2k3","Value":0.0},{"Source":"N3","Destination":"N7","Commodity":"S2T2k3","Value":0.0},{"Source":"N4","Destination":"N3","Commodity":"S2T2k3","Value":0.0},{"Source":"N4","Destination":"N5","Commodity":"S2T2k3","Value":0.0},{"Source":"N5","Destination":"N2","Commodity":"S2T2k3","Value":0.0},{"Source":"N5","Destination":"N3","Commodity":"S2T2k3","Value":0.0},{"Source":"N5","Destination":"N4","Commodity":"S2T2k3","Value":0.0},{"Source":"N5","Destination":"N6","Commodity":"S2T2k3","Value":0.0},{"Source":"N5","Destination":"N7","Commodity":"S2T2k3","Value":0.0},{"Source":"N5","Destination":"N8","Commodity":"S2T2k3","Value":0.0},{"Source":"N6","Destination":"N1","Commodity":"S2T2k3","Value":0.0},{"Source":"N6","Destination":"N2","Commodity":"S2T2k3","Value":0.0},{"Source":"N6","Destination":"N5","Commodity":"S2T2k3","Value":0.0},{"Source":"N6","Destination":"N7","Commodity":"S2T2k3","Value":0.0},{"Source":"N7","Destination":"N2","Commodity":"S2T2k3","Value":0.0},{"Source":"N7","Destination":"N3","Commodity":"S2T2k3","Value":0.0},{"Source":"N7","Destination":"N5","Commodity":"S2T2k3","Value":0.0},{"Source":"N7","Destination":"N6","Commodity":"S2T2k3","Value":0.0},{"Source":"N7","Destination":"N8","Commodity":"S2T2k3","Value":0.0},{"Source":"N8","Destination":"N5","Commodity":"S2T2k3","Value":0.0},{"Source":"N8","Destination":"N7","Commodity":"S2T2k3","Value":0.0},{"Source":"T1","Destination":"T1k1","Commodity":"S2T2k3","Value":0.0},{"Source":"S1","Destination":"T1k1","Commodity":"S2T2k3","Value":0.0},{"Source":"T2","Destination":"T2k2","Commodity":"S2T2k3","Value":0.0},{"Source":"S1","Destination":"T2k2","Commodity":"S2T2k3","Value":0.0},{"Source":"T2","Destination":"T2k3","Commodity":"S2T2k3","Value":1.0},{"Source":"S2","Destination":"T2k3","Commodity":"S2T2k3","Value":0.0},{"Source":"T1","Destination":"T1k4","Commodity":"S2T2k3","Value":0.0},{"Source":"S2","Destination":"T1k4","Commodity":"S2T2k3","Value":0.0},{"Source":"N6","Destination":"T2","Commodity":"S2T2k3","Value":0.0},{"Source":"N7","Destination":"T2","Commodity":"S2T2k3","Value":1.0},{"Source":"N8","Destination":"T2","Commodity":"S2T2k3","Value":0.0},{"Source":"T2","Destination":"T2k4","Commodity":"S2T2k3","Value":0.0},{"Source":"S2","Destination":"T2k4","Commodity":"S2T2k3","Value":0.0},{"Source":"T3","Destination":"T3k4","Commodity":"S2T2k3","Value":0.0},{"Source":"S2","Destination":"T3k4","Commodity":"S2T2k3","Value":0.0},{"Source":"T3","Destination":"T3k5","Commodity":"S2T2k3","Value":0.0},{"Source":"S3","Destination":"T3k5","Commodity":"S2T2k3","Value":0.0},{"Source":"N6","Destination":"T1","Commodity":"S2T2k3","Value":0.0},{"Source":"N7","Destination":"T1","Commodity":"S2T2k3","Value":0.0},{"Source":"T1","Destination":"T1k6","Commodity":"S2T2k3","Value":0.0},{"Source":"S3","Destination":"T1k6","Commodity":"S2T2k3","Value":0.0},{"Source":"N5","Destination":"T3","Commodity":"S2T2k3","Value":0.0},{"Source":"N8","Destination":"T3","Commodity":"S2T2k3","Value":0.0},{"Source":"T3","Destination":"T3k6","Commodity":"S2T2k3","Value":0.0},{"Source":"S3","Destination":"T3k6","Commodity":"S2T2k3","Value":0.0},{"Source":"S1","Destination":"N1","Commodity":"S2T1k4","Value":0.0},{"Source":"S1","Destination":"N3","Commodity":"S2T1k4","Value":0.0},{"Source":"S2","Destination":"N2","Commodity":"S2T1k4","Value":1.0},{"Source":"S2","Destination":"N4","Commodity":"S2T1k4","Value":0.0},{"Source":"S3","Destination":"N3","Commodity":"S2T1k4","Value":0.0},{"Source":"S3","Destination":"N5","Commodity":"S2T1k4","Value":0.0},{"Source":"N1","Destination":"N2","Commodity":"S2T1k4","Value":0.0},{"Source":"N1","Destination":"N6","Commodity":"S2T1k4","Value":0.0},{"Source":"N2","Destination":"N1","Commodity":"S2T1k4","Value":0.0},{"Source":"N2","Destination":"N3","Commodity":"S2T1k4","Value":0.0},{"Source":"N2","Destination":"N5","Commodity":"S2T1k4","Value":0.0},{"Source":"N2","Destination":"N6","Commodity":"S2T1k4","Value":1.0},{"Source":"N2","Destination":"N7","Commodity":"S2T1k4","Value":0.0},{"Source":"N3","Destination":"N2","Commodity":"S2T1k4","Value":0.0},{"Source":"N3","Destination":"N4","Commodity":"S2T1k4","Value":0.0},{"Source":"N3","Destination":"N5","Commodity":"S2T1k4","Value":0.0},{"Source":"N3","Destination":"N7","Commodity":"S2T1k4","Value":0.0},{"Source":"N4","Destination":"N3","Commodity":"S2T1k4","Value":0.0},{"Source":"N4","Destination":"N5","Commodity":"S2T1k4","Value":0.0},{"Source":"N5","Destination":"N2","Commodity":"S2T1k4","Value":0.0},{"Source":"N5","Destination":"N3","Commodity":"S2T1k4","Value":0.0},{"Source":"N5","Destination":"N4","Commodity":"S2T1k4","Value":0.0},{"Source":"N5","Destination":"N6","Commodity":"S2T1k4","Value":0.0},{"Source":"N5","Destination":"N7","Commodity":"S2T1k4","Value":0.0},{"Source":"N5","Destination":"N8","Commodity":"S2T1k4","Value":0.0},{"Source":"N6","Destination":"N1","Commodity":"S2T1k4","Value":0.0},{"Source":"N6","Destination":"N2","Commodity":"S2T1k4","Value":0.0},{"Source":"N6","Destination":"N5","Commodity":"S2T1k4","Value":0.0},{"Source":"N6","Destination":"N7","Commodity":"S2T1k4","Value":0.0},{"Source":"N7","Destination":"N2","Commodity":"S2T1k4","Value":0.0},{"Source":"N7","Destination":"N3","Commodity":"S2T1k4","Value":0.0},{"Source":"N7","Destination":"N5","Commodity":"S2T1k4","Value":0.0},{"Source":"N7","Destination":"N6","Commodity":"S2T1k4","Value":0.0},{"Source":"N7","Destination":"N8","Commodity":"S2T1k4","Value":0.0},{"Source":"N8","Destination":"N5","Commodity":"S2T1k4","Value":0.0},{"Source":"N8","Destination":"N7","Commodity":"S2T1k4","Value":0.0},{"Source":"T1","Destination":"T1k1","Commodity":"S2T1k4","Value":0.0},{"Source":"S1","Destination":"T1k1","Commodity":"S2T1k4","Value":0.0},{"Source":"T2","Destination":"T2k2","Commodity":"S2T1k4","Value":0.0},{"Source":"S1","Destination":"T2k2","Commodity":"S2T1k4","Value":0.0},{"Source":"T2","Destination":"T2k3","Commodity":"S2T1k4","Value":0.0},{"Source":"S2","Destination":"T2k3","Commodity":"S2T1k4","Value":0.0},{"Source":"T1","Destination":"T1k4","Commodity":"S2T1k4","Value":1.0},{"Source":"S2","Destination":"T1k4","Commodity":"S2T1k4","Value":0.0},{"Source":"N6","Destination":"T2","Commodity":"S2T1k4","Value":0.0},{"Source":"N7","Destination":"T2","Commodity":"S2T1k4","Value":0.0},{"Source":"N8","Destination":"T2","Commodity":"S2T1k4","Value":0.0},{"Source":"T2","Destination":"T2k4","Commodity":"S2T1k4","Value":0.0},{"Source":"S2","Destination":"T2k4","Commodity":"S2T1k4","Value":0.0},{"Source":"T3","Destination":"T3k4","Commodity":"S2T1k4","Value":0.0},{"Source":"S2","Destination":"T3k4","Commodity":"S2T1k4","Value":0.0},{"Source":"T3","Destination":"T3k5","Commodity":"S2T1k4","Value":0.0},{"Source":"S3","Destination":"T3k5","Commodity":"S2T1k4","Value":0.0},{"Source":"N6","Destination":"T1","Commodity":"S2T1k4","Value":1.0},{"Source":"N7","Destination":"T1","Commodity":"S2T1k4","Value":0.0},{"Source":"T1","Destination":"T1k6","Commodity":"S2T1k4","Value":0.0},{"Source":"S3","Destination":"T1k6","Commodity":"S2T1k4","Value":0.0},{"Source":"N5","Destination":"T3","Commodity":"S2T1k4","Value":0.0},{"Source":"N8","Destination":"T3","Commodity":"S2T1k4","Value":0.0},{"Source":"T3","Destination":"T3k6","Commodity":"S2T1k4","Value":0.0},{"Source":"S3","Destination":"T3k6","Commodity":"S2T1k4","Value":0.0},{"Source":"S1","Destination":"N1","Commodity":"S3T3k5","Value":0.0},{"Source":"S1","Destination":"N3","Commodity":"S3T3k5","Value":0.0},{"Source":"S2","Destination":"N2","Commodity":"S3T3k5","Value":0.0},{"Source":"S2","Destination":"N4","Commodity":"S3T3k5","Value":0.0},{"Source":"S3","Destination":"N3","Commodity":"S3T3k5","Value":0.0},{"Source":"S3","Destination":"N5","Commodity":"S3T3k5","Value":1.0},{"Source":"N1","Destination":"N2","Commodity":"S3T3k5","Value":0.0},{"Source":"N1","Destination":"N6","Commodity":"S3T3k5","Value":0.0},{"Source":"N2","Destination":"N1","Commodity":"S3T3k5","Value":0.0},{"Source":"N2","Destination":"N3","Commodity":"S3T3k5","Value":0.0},{"Source":"N2","Destination":"N5","Commodity":"S3T3k5","Value":0.0},{"Source":"N2","Destination":"N6","Commodity":"S3T3k5","Value":0.0},{"Source":"N2","Destination":"N7","Commodity":"S3T3k5","Value":0.0},{"Source":"N3","Destination":"N2","Commodity":"S3T3k5","Value":0.0},{"Source":"N3","Destination":"N4","Commodity":"S3T3k5","Value":0.0},{"Source":"N3","Destination":"N5","Commodity":"S3T3k5","Value":0.0},{"Source":"N3","Destination":"N7","Commodity":"S3T3k5","Value":0.0},{"Source":"N4","Destination":"N3","Commodity":"S3T3k5","Value":0.0},{"Source":"N4","Destination":"N5","Commodity":"S3T3k5","Value":0.0},{"Source":"N5","Destination":"N2","Commodity":"S3T3k5","Value":0.0},{"Source":"N5","Destination":"N3","Commodity":"S3T3k5","Value":0.0},{"Source":"N5","Destination":"N4","Commodity":"S3T3k5","Value":0.0},{"Source":"N5","Destination":"N6","Commodity":"S3T3k5","Value":0.0},{"Source":"N5","Destination":"N7","Commodity":"S3T3k5","Value":0.0},{"Source":"N5","Destination":"N8","Commodity":"S3T3k5","Value":0.0},{"Source":"N6","Destination":"N1","Commodity":"S3T3k5","Value":0.0},{"Source":"N6","Destination":"N2","Commodity":"S3T3k5","Value":0.0},{"Source":"N6","Destination":"N5","Commodity":"S3T3k5","Value":0.0},{"Source":"N6","Destination":"N7","Commodity":"S3T3k5","Value":0.0},{"Source":"N7","Destination":"N2","Commodity":"S3T3k5","Value":0.0},{"Source":"N7","Destination":"N3","Commodity":"S3T3k5","Value":0.0},{"Source":"N7","Destination":"N5","Commodity":"S3T3k5","Value":0.0},{"Source":"N7","Destination":"N6","Commodity":"S3T3k5","Value":0.0},{"Source":"N7","Destination":"N8","Commodity":"S3T3k5","Value":0.0},{"Source":"N8","Destination":"N5","Commodity":"S3T3k5","Value":0.0},{"Source":"N8","Destination":"N7","Commodity":"S3T3k5","Value":0.0},{"Source":"T1","Destination":"T1k1","Commodity":"S3T3k5","Value":0.0},{"Source":"S1","Destination":"T1k1","Commodity":"S3T3k5","Value":0.0},{"Source":"T2","Destination":"T2k2","Commodity":"S3T3k5","Value":0.0},{"Source":"S1","Destination":"T2k2","Commodity":"S3T3k5","Value":0.0},{"Source":"T2","Destination":"T2k3","Commodity":"S3T3k5","Value":0.0},{"Source":"S2","Destination":"T2k3","Commodity":"S3T3k5","Value":0.0},{"Source":"T1","Destination":"T1k4","Commodity":"S3T3k5","Value":0.0},{"Source":"S2","Destination":"T1k4","Commodity":"S3T3k5","Value":0.0},{"Source":"N6","Destination":"T2","Commodity":"S3T3k5","Value":0.0},{"Source":"N7","Destination":"T2","Commodity":"S3T3k5","Value":0.0},{"Source":"N8","Destination":"T2","Commodity":"S3T3k5","Value":0.0},{"Source":"T2","Destination":"T2k4","Commodity":"S3T3k5","Value":0.0},{"Source":"S2","Destination":"T2k4","Commodity":"S3T3k5","Value":0.0},{"Source":"T3","Destination":"T3k4","Commodity":"S3T3k5","Value":0.0},{"Source":"S2","Destination":"T3k4","Commodity":"S3T3k5","Value":0.0},{"Source":"T3","Destination":"T3k5","Commodity":"S3T3k5","Value":1.0},{"Source":"S3","Destination":"T3k5","Commodity":"S3T3k5","Value":0.0},{"Source":"N6","Destination":"T1","Commodity":"S3T3k5","Value":0.0},{"Source":"N7","Destination":"T1","Commodity":"S3T3k5","Value":0.0},{"Source":"T1","Destination":"T1k6","Commodity":"S3T3k5","Value":0.0},{"Source":"S3","Destination":"T1k6","Commodity":"S3T3k5","Value":0.0},{"Source":"N5","Destination":"T3","Commodity":"S3T3k5","Value":1.0},{"Source":"N8","Destination":"T3","Commodity":"S3T3k5","Value":0.0},{"Source":"T3","Destination":"T3k6","Commodity":"S3T3k5","Value":0.0},{"Source":"S3","Destination":"T3k6","Commodity":"S3T3k5","Value":0.0},{"Source":"S1","Destination":"N1","Commodity":"S3T1k6","Value":0.0},{"Source":"S1","Destination":"N3","Commodity":"S3T1k6","Value":0.0},{"Source":"S2","Destination":"N2","Commodity":"S3T1k6","Value":0.0},{"Source":"S2","Destination":"N4","Commodity":"S3T1k6","Value":0.0},{"Source":"S3","Destination":"N3","Commodity":"S3T1k6","Value":0.0},{"Source":"S3","Destination":"N5","Commodity":"S3T1k6","Value":1.0},{"Source":"N1","Destination":"N2","Commodity":"S3T1k6","Value":0.0},{"Source":"N1","Destination":"N6","Commodity":"S3T1k6","Value":0.0},{"Source":"N2","Destination":"N1","Commodity":"S3T1k6","Value":0.0},{"Source":"N2","Destination":"N3","Commodity":"S3T1k6","Value":0.0},{"Source":"N2","Destination":"N5","Commodity":"S3T1k6","Value":0.0},{"Source":"N2","Destination":"N6","Commodity":"S3T1k6","Value":0.0},{"Source":"N2","Destination":"N7","Commodity":"S3T1k6","Value":0.0},{"Source":"N3","Destination":"N2","Commodity":"S3T1k6","Value":0.0},{"Source":"N3","Destination":"N4","Commodity":"S3T1k6","Value":0.0},{"Source":"N3","Destination":"N5","Commodity":"S3T1k6","Value":0.0},{"Source":"N3","Destination":"N7","Commodity":"S3T1k6","Value":0.0},{"Source":"N4","Destination":"N3","Commodity":"S3T1k6","Value":0.0},{"Source":"N4","Destination":"N5","Commodity":"S3T1k6","Value":0.0},{"Source":"N5","Destination":"N2","Commodity":"S3T1k6","Value":0.0},{"Source":"N5","Destination":"N3","Commodity":"S3T1k6","Value":0.0},{"Source":"N5","Destination":"N4","Commodity":"S3T1k6","Value":0.0},{"Source":"N5","Destination":"N6","Commodity":"S3T1k6","Value":0.0},{"Source":"N5","Destination":"N7","Commodity":"S3T1k6","Value":1.0},{"Source":"N5","Destination":"N8","Commodity":"S3T1k6","Value":0.0},{"Source":"N6","Destination":"N1","Commodity":"S3T1k6","Value":0.0},{"Source":"N6","Destination":"N2","Commodity":"S3T1k6","Value":0.0},{"Source":"N6","Destination":"N5","Commodity":"S3T1k6","Value":0.0},{"Source":"N6","Destination":"N7","Commodity":"S3T1k6","Value":0.0},{"Source":"N7","Destination":"N2","Commodity":"S3T1k6","Value":0.0},{"Source":"N7","Destination":"N3","Commodity":"S3T1k6","Value":0.0},{"Source":"N7","Destination":"N5","Commodity":"S3T1k6","Value":0.0},{"Source":"N7","Destination":"N6","Commodity":"S3T1k6","Value":0.0},{"Source":"N7","Destination":"N8","Commodity":"S3T1k6","Value":0.0},{"Source":"N8","Destination":"N5","Commodity":"S3T1k6","Value":0.0},{"Source":"N8","Destination":"N7","Commodity":"S3T1k6","Value":0.0},{"Source":"T1","Destination":"T1k1","Commodity":"S3T1k6","Value":0.0},{"Source":"S1","Destination":"T1k1","Commodity":"S3T1k6","Value":0.0},{"Source":"T2","Destination":"T2k2","Commodity":"S3T1k6","Value":0.0},{"Source":"S1","Destination":"T2k2","Commodity":"S3T1k6","Value":0.0},{"Source":"T2","Destination":"T2k3","Commodity":"S3T1k6","Value":0.0},{"Source":"S2","Destination":"T2k3","Commodity":"S3T1k6","Value":0.0},{"Source":"T1","Destination":"T1k4","Commodity":"S3T1k6","Value":0.0},{"Source":"S2","Destination":"T1k4","Commodity":"S3T1k6","Value":0.0},{"Source":"N6","Destination":"T2","Commodity":"S3T1k6","Value":0.0},{"Source":"N7","Destination":"T2","Commodity":"S3T1k6","Value":0.0},{"Source":"N8","Destination":"T2","Commodity":"S3T1k6","Value":0.0},{"Source":"T2","Destination":"T2k4","Commodity":"S3T1k6","Value":0.0},{"Source":"S2","Destination":"T2k4","Commodity":"S3T1k6","Value":0.0},{"Source":"T3","Destination":"T3k4","Commodity":"S3T1k6","Value":0.0},{"Source":"S2","Destination":"T3k4","Commodity":"S3T1k6","Value":0.0},{"Source":"T3","Destination":"T3k5","Commodity":"S3T1k6","Value":0.0},{"Source":"S3","Destination":"T3k5","Commodity":"S3T1k6","Value":0.0},{"Source":"N6","Destination":"T1","Commodity":"S3T1k6","Value":0.0},{"Source":"N7","Destination":"T1","Commodity":"S3T1k6","Value":1.0},{"Source":"T1","Destination":"T1k6","Commodity":"S3T1k6","Value":1.0},{"Source":"S3","Destination":"T1k6","Commodity":"S3T1k6","Value":0.0},{"Source":"N5","Destination":"T3","Commodity":"S3T1k6","Value":0.0},{"Source":"N8","Destination":"T3","Commodity":"S3T1k6","Value":0.0},{"Source":"T3","Destination":"T3k6","Commodity":"S3T1k6","Value":0.0},{"Source":"S3","Destination":"T3k6","Commodity":"S3T1k6","Value":0.0},{"Source":"S1","Destination":"N1","Commodity":"S1T1k1","Value":0.0},{"Source":"S1","Destination":"N3","Commodity":"S1T1k1","Value":1.0},{"Source":"S2","Destination":"N2","Commodity":"S1T1k1","Value":0.0},{"Source":"S2","Destination":"N4","Commodity":"S1T1k1","Value":0.0},{"Source":"S3","Destination":"N3","Commodity":"S1T1k1","Value":0.0},{"Source":"S3","Destination":"N5","Commodity":"S1T1k1","Value":0.0},{"Source":"N1","Destination":"N2","Commodity":"S1T1k1","Value":0.0},{"Source":"N1","Destination":"N6","Commodity":"S1T1k1","Value":0.0},{"Source":"N2","Destination":"N1","Commodity":"S1T1k1","Value":0.0},{"Source":"N2","Destination":"N3","Commodity":"S1T1k1","Value":0.0},{"Source":"N2","Destination":"N5","Commodity":"S1T1k1","Value":0.0},{"Source":"N2","Destination":"N6","Commodity":"S1T1k1","Value":0.0},{"Source":"N2","Destination":"N7","Commodity":"S1T1k1","Value":0.0},{"Source":"N3","Destination":"N2","Commodity":"S1T1k1","Value":0.0},{"Source":"N3","Destination":"N4","Commodity":"S1T1k1","Value":0.0},{"Source":"N3","Destination":"N5","Commodity":"S1T1k1","Value":0.0},{"Source":"N3","Destination":"N7","Commodity":"S1T1k1","Value":1.0},{"Source":"N4","Destination":"N3","Commodity":"S1T1k1","Value":0.0},{"Source":"N4","Destination":"N5","Commodity":"S1T1k1","Value":0.0},{"Source":"N5","Destination":"N2","Commodity":"S1T1k1","Value":0.0},{"Source":"N5","Destination":"N3","Commodity":"S1T1k1","Value":0.0},{"Source":"N5","Destination":"N4","Commodity":"S1T1k1","Value":0.0},{"Source":"N5","Destination":"N6","Commodity":"S1T1k1","Value":0.0},{"Source":"N5","Destination":"N7","Commodity":"S1T1k1","Value":0.0},{"Source":"N5","Destination":"N8","Commodity":"S1T1k1","Value":0.0},{"Source":"N6","Destination":"N1","Commodity":"S1T1k1","Value":0.0},{"Source":"N6","Destination":"N2","Commodity":"S1T1k1","Value":0.0},{"Source":"N6","Destination":"N5","Commodity":"S1T1k1","Value":0.0},{"Source":"N6","Destination":"N7","Commodity":"S1T1k1","Value":0.0},{"Source":"N7","Destination":"N2","Commodity":"S1T1k1","Value":0.0},{"Source":"N7","Destination":"N3","Commodity":"S1T1k1","Value":0.0},{"Source":"N7","Destination":"N5","Commodity":"S1T1k1","Value":0.0},{"Source":"N7","Destination":"N6","Commodity":"S1T1k1","Value":0.0},{"Source":"N7","Destination":"N8","Commodity":"S1T1k1","Value":0.0},{"Source":"N8","Destination":"N5","Commodity":"S1T1k1","Value":0.0},{"Source":"N8","Destination":"N7","Commodity":"S1T1k1","Value":0.0},{"Source":"T1","Destination":"T1k1","Commodity":"S1T1k1","Value":1.0},{"Source":"S1","Destination":"T1k1","Commodity":"S1T1k1","Value":0.0},{"Source":"T2","Destination":"T2k2","Commodity":"S1T1k1","Value":0.0},{"Source":"S1","Destination":"T2k2","Commodity":"S1T1k1","Value":0.0},{"Source":"T2","Destination":"T2k3","Commodity":"S1T1k1","Value":0.0},{"Source":"S2","Destination":"T2k3","Commodity":"S1T1k1","Value":0.0},{"Source":"T1","Destination":"T1k4","Commodity":"S1T1k1","Value":0.0},{"Source":"S2","Destination":"T1k4","Commodity":"S1T1k1","Value":0.0},{"Source":"N6","Destination":"T2","Commodity":"S1T1k1","Value":0.0},{"Source":"N7","Destination":"T2","Commodity":"S1T1k1","Value":0.0},{"Source":"N8","Destination":"T2","Commodity":"S1T1k1","Value":0.0},{"Source":"T2","Destination":"T2k4","Commodity":"S1T1k1","Value":0.0},{"Source":"S2","Destination":"T2k4","Commodity":"S1T1k1","Value":0.0},{"Source":"T3","Destination":"T3k4","Commodity":"S1T1k1","Value":0.0},{"Source":"S2","Destination":"T3k4","Commodity":"S1T1k1","Value":0.0},{"Source":"T3","Destination":"T3k5","Commodity":"S1T1k1","Value":0.0},{"Source":"S3","Destination":"T3k5","Commodity":"S1T1k1","Value":0.0},{"Source":"N6","Destination":"T1","Commodity":"S1T1k1","Value":0.0},{"Source":"N7","Destination":"T1","Commodity":"S1T1k1","Value":1.0},{"Source":"T1","Destination":"T1k6","Commodity":"S1T1k1","Value":0.0},{"Source":"S3","Destination":"T1k6","Commodity":"S1T1k1","Value":0.0},{"Source":"N5","Destination":"T3","Commodity":"S1T1k1","Value":0.0},{"Source":"N8","Destination":"T3","Commodity":"S1T1k1","Value":0.0},{"Source":"T3","Destination":"T3k6","Commodity":"S1T1k1","Value":0.0},{"Source":"S3","Destination":"T3k6","Commodity":"S1T1k1","Value":0.0},{"Source":"S1","Destination":"N1","Commodity":"S2T2k4","Value":0.0},{"Source":"S1","Destination":"N3","Commodity":"S2T2k4","Value":0.0},{"Source":"S2","Destination":"N2","Commodity":"S2T2k4","Value":1.0},{"Source":"S2","Destination":"N4","Commodity":"S2T2k4","Value":0.0},{"Source":"S3","Destination":"N3","Commodity":"S2T2k4","Value":0.0},{"Source":"S3","Destination":"N5","Commodity":"S2T2k4","Value":0.0},{"Source":"N1","Destination":"N2","Commodity":"S2T2k4","Value":0.0},{"Source":"N1","Destination":"N6","Commodity":"S2T2k4","Value":0.0},{"Source":"N2","Destination":"N1","Commodity":"S2T2k4","Value":0.0},{"Source":"N2","Destination":"N3","Commodity":"S2T2k4","Value":0.0},{"Source":"N2","Destination":"N5","Commodity":"S2T2k4","Value":0.0},{"Source":"N2","Destination":"N6","Commodity":"S2T2k4","Value":1.0},{"Source":"N2","Destination":"N7","Commodity":"S2T2k4","Value":0.0},{"Source":"N3","Destination":"N2","Commodity":"S2T2k4","Value":0.0},{"Source":"N3","Destination":"N4","Commodity":"S2T2k4","Value":0.0},{"Source":"N3","Destination":"N5","Commodity":"S2T2k4","Value":0.0},{"Source":"N3","Destination":"N7","Commodity":"S2T2k4","Value":0.0},{"Source":"N4","Destination":"N3","Commodity":"S2T2k4","Value":0.0},{"Source":"N4","Destination":"N5","Commodity":"S2T2k4","Value":0.0},{"Source":"N5","Destination":"N2","Commodity":"S2T2k4","Value":0.0},{"Source":"N5","Destination":"N3","Commodity":"S2T2k4","Value":0.0},{"Source":"N5","Destination":"N4","Commodity":"S2T2k4","Value":0.0},{"Source":"N5","Destination":"N6","Commodity":"S2T2k4","Value":0.0},{"Source":"N5","Destination":"N7","Commodity":"S2T2k4","Value":0.0},{"Source":"N5","Destination":"N8","Commodity":"S2T2k4","Value":0.0},{"Source":"N6","Destination":"N1","Commodity":"S2T2k4","Value":0.0},{"Source":"N6","Destination":"N2","Commodity":"S2T2k4","Value":0.0},{"Source":"N6","Destination":"N5","Commodity":"S2T2k4","Value":0.0},{"Source":"N6","Destination":"N7","Commodity":"S2T2k4","Value":0.0},{"Source":"N7","Destination":"N2","Commodity":"S2T2k4","Value":0.0},{"Source":"N7","Destination":"N3","Commodity":"S2T2k4","Value":0.0},{"Source":"N7","Destination":"N5","Commodity":"S2T2k4","Value":0.0},{"Source":"N7","Destination":"N6","Commodity":"S2T2k4","Value":0.0},{"Source":"N7","Destination":"N8","Commodity":"S2T2k4","Value":0.0},{"Source":"N8","Destination":"N5","Commodity":"S2T2k4","Value":0.0},{"Source":"N8","Destination":"N7","Commodity":"S2T2k4","Value":0.0},{"Source":"T1","Destination":"T1k1","Commodity":"S2T2k4","Value":0.0},{"Source":"S1","Destination":"T1k1","Commodity":"S2T2k4","Value":0.0},{"Source":"T2","Destination":"T2k2","Commodity":"S2T2k4","Value":0.0},{"Source":"S1","Destination":"T2k2","Commodity":"S2T2k4","Value":0.0},{"Source":"T2","Destination":"T2k3","Commodity":"S2T2k4","Value":0.0},{"Source":"S2","Destination":"T2k3","Commodity":"S2T2k4","Value":0.0},{"Source":"T1","Destination":"T1k4","Commodity":"S2T2k4","Value":0.0},{"Source":"S2","Destination":"T1k4","Commodity":"S2T2k4","Value":0.0},{"Source":"N6","Destination":"T2","Commodity":"S2T2k4","Value":1.0},{"Source":"N7","Destination":"T2","Commodity":"S2T2k4","Value":0.0},{"Source":"N8","Destination":"T2","Commodity":"S2T2k4","Value":0.0},{"Source":"T2","Destination":"T2k4","Commodity":"S2T2k4","Value":1.0},{"Source":"S2","Destination":"T2k4","Commodity":"S2T2k4","Value":0.0},{"Source":"T3","Destination":"T3k4","Commodity":"S2T2k4","Value":0.0},{"Source":"S2","Destination":"T3k4","Commodity":"S2T2k4","Value":0.0},{"Source":"T3","Destination":"T3k5","Commodity":"S2T2k4","Value":0.0},{"Source":"S3","Destination":"T3k5","Commodity":"S2T2k4","Value":0.0},{"Source":"N6","Destination":"T1","Commodity":"S2T2k4","Value":0.0},{"Source":"N7","Destination":"T1","Commodity":"S2T2k4","Value":0.0},{"Source":"T1","Destination":"T1k6","Commodity":"S2T2k4","Value":0.0},{"Source":"S3","Destination":"T1k6","Commodity":"S2T2k4","Value":0.0},{"Source":"N5","Destination":"T3","Commodity":"S2T2k4","Value":0.0},{"Source":"N8","Destination":"T3","Commodity":"S2T2k4","Value":0.0},{"Source":"T3","Destination":"T3k6","Commodity":"S2T2k4","Value":0.0},{"Source":"S3","Destination":"T3k6","Commodity":"S2T2k4","Value":0.0},{"Source":"S1","Destination":"N1","Commodity":"S2T3k4","Value":0.0},{"Source":"S1","Destination":"N3","Commodity":"S2T3k4","Value":0.0},{"Source":"S2","Destination":"N2","Commodity":"S2T3k4","Value":1.0},{"Source":"S2","Destination":"N4","Commodity":"S2T3k4","Value":0.0},{"Source":"S3","Destination":"N3","Commodity":"S2T3k4","Value":0.0},{"Source":"S3","Destination":"N5","Commodity":"S2T3k4","Value":0.0},{"Source":"N1","Destination":"N2","Commodity":"S2T3k4","Value":0.0},{"Source":"N1","Destination":"N6","Commodity":"S2T3k4","Value":0.0},{"Source":"N2","Destination":"N1","Commodity":"S2T3k4","Value":0.0},{"Source":"N2","Destination":"N3","Commodity":"S2T3k4","Value":0.0},{"Source":"N2","Destination":"N5","Commodity":"S2T3k4","Value":0.0},{"Source":"N2","Destination":"N6","Commodity":"S2T3k4","Value":1.0},{"Source":"N2","Destination":"N7","Commodity":"S2T3k4","Value":0.0},{"Source":"N3","Destination":"N2","Commodity":"S2T3k4","Value":0.0},{"Source":"N3","Destination":"N4","Commodity":"S2T3k4","Value":0.0},{"Source":"N3","Destination":"N5","Commodity":"S2T3k4","Value":0.0},{"Source":"N3","Destination":"N7","Commodity":"S2T3k4","Value":0.0},{"Source":"N4","Destination":"N3","Commodity":"S2T3k4","Value":0.0},{"Source":"N4","Destination":"N5","Commodity":"S2T3k4","Value":0.0},{"Source":"N5","Destination":"N2","Commodity":"S2T3k4","Value":0.0},{"Source":"N5","Destination":"N3","Commodity":"S2T3k4","Value":0.0},{"Source":"N5","Destination":"N4","Commodity":"S2T3k4","Value":0.0},{"Source":"N5","Destination":"N6","Commodity":"S2T3k4","Value":0.0},{"Source":"N5","Destination":"N7","Commodity":"S2T3k4","Value":0.0},{"Source":"N5","Destination":"N8","Commodity":"S2T3k4","Value":0.0},{"Source":"N6","Destination":"N1","Commodity":"S2T3k4","Value":0.0},{"Source":"N6","Destination":"N2","Commodity":"S2T3k4","Value":0.0},{"Source":"N6","Destination":"N5","Commodity":"S2T3k4","Value":1.0},{"Source":"N6","Destination":"N7","Commodity":"S2T3k4","Value":0.0},{"Source":"N7","Destination":"N2","Commodity":"S2T3k4","Value":0.0},{"Source":"N7","Destination":"N3","Commodity":"S2T3k4","Value":0.0},{"Source":"N7","Destination":"N5","Commodity":"S2T3k4","Value":0.0},{"Source":"N7","Destination":"N6","Commodity":"S2T3k4","Value":0.0},{"Source":"N7","Destination":"N8","Commodity":"S2T3k4","Value":0.0},{"Source":"N8","Destination":"N5","Commodity":"S2T3k4","Value":0.0},{"Source":"N8","Destination":"N7","Commodity":"S2T3k4","Value":0.0},{"Source":"T1","Destination":"T1k1","Commodity":"S2T3k4","Value":0.0},{"Source":"S1","Destination":"T1k1","Commodity":"S2T3k4","Value":0.0},{"Source":"T2","Destination":"T2k2","Commodity":"S2T3k4","Value":0.0},{"Source":"S1","Destination":"T2k2","Commodity":"S2T3k4","Value":0.0},{"Source":"T2","Destination":"T2k3","Commodity":"S2T3k4","Value":0.0},{"Source":"S2","Destination":"T2k3","Commodity":"S2T3k4","Value":0.0},{"Source":"T1","Destination":"T1k4","Commodity":"S2T3k4","Value":0.0},{"Source":"S2","Destination":"T1k4","Commodity":"S2T3k4","Value":0.0},{"Source":"N6","Destination":"T2","Commodity":"S2T3k4","Value":0.0},{"Source":"N7","Destination":"T2","Commodity":"S2T3k4","Value":0.0},{"Source":"N8","Destination":"T2","Commodity":"S2T3k4","Value":0.0},{"Source":"T2","Destination":"T2k4","Commodity":"S2T3k4","Value":0.0},{"Source":"S2","Destination":"T2k4","Commodity":"S2T3k4","Value":0.0},{"Source":"T3","Destination":"T3k4","Commodity":"S2T3k4","Value":1.0},{"Source":"S2","Destination":"T3k4","Commodity":"S2T3k4","Value":0.0},{"Source":"T3","Destination":"T3k5","Commodity":"S2T3k4","Value":0.0},{"Source":"S3","Destination":"T3k5","Commodity":"S2T3k4","Value":0.0},{"Source":"N6","Destination":"T1","Commodity":"S2T3k4","Value":0.0},{"Source":"N7","Destination":"T1","Commodity":"S2T3k4","Value":0.0},{"Source":"T1","Destination":"T1k6","Commodity":"S2T3k4","Value":0.0},{"Source":"S3","Destination":"T1k6","Commodity":"S2T3k4","Value":0.0},{"Source":"N5","Destination":"T3","Commodity":"S2T3k4","Value":1.0},{"Source":"N8","Destination":"T3","Commodity":"S2T3k4","Value":0.0},{"Source":"T3","Destination":"T3k6","Commodity":"S2T3k4","Value":0.0},{"Source":"S3","Destination":"T3k6","Commodity":"S2T3k4","Value":0.0},{"Source":"S1","Destination":"N1","Commodity":"S3T3k6","Value":0.0},{"Source":"S1","Destination":"N3","Commodity":"S3T3k6","Value":0.0},{"Source":"S2","Destination":"N2","Commodity":"S3T3k6","Value":0.0},{"Source":"S2","Destination":"N4","Commodity":"S3T3k6","Value":0.0},{"Source":"S3","Destination":"N3","Commodity":"S3T3k6","Value":0.0},{"Source":"S3","Destination":"N5","Commodity":"S3T3k6","Value":1.0},{"Source":"N1","Destination":"N2","Commodity":"S3T3k6","Value":0.0},{"Source":"N1","Destination":"N6","Commodity":"S3T3k6","Value":0.0},{"Source":"N2","Destination":"N1","Commodity":"S3T3k6","Value":0.0},{"Source":"N2","Destination":"N3","Commodity":"S3T3k6","Value":0.0},{"Source":"N2","Destination":"N5","Commodity":"S3T3k6","Value":0.0},{"Source":"N2","Destination":"N6","Commodity":"S3T3k6","Value":0.0},{"Source":"N2","Destination":"N7","Commodity":"S3T3k6","Value":0.0},{"Source":"N3","Destination":"N2","Commodity":"S3T3k6","Value":0.0},{"Source":"N3","Destination":"N4","Commodity":"S3T3k6","Value":0.0},{"Source":"N3","Destination":"N5","Commodity":"S3T3k6","Value":0.0},{"Source":"N3","Destination":"N7","Commodity":"S3T3k6","Value":0.0},{"Source":"N4","Destination":"N3","Commodity":"S3T3k6","Value":0.0},{"Source":"N4","Destination":"N5","Commodity":"S3T3k6","Value":0.0},{"Source":"N5","Destination":"N2","Commodity":"S3T3k6","Value":0.0},{"Source":"N5","Destination":"N3","Commodity":"S3T3k6","Value":0.0},{"Source":"N5","Destination":"N4","Commodity":"S3T3k6","Value":0.0},{"Source":"N5","Destination":"N6","Commodity":"S3T3k6","Value":0.0},{"Source":"N5","Destination":"N7","Commodity":"S3T3k6","Value":0.0},{"Source":"N5","Destination":"N8","Commodity":"S3T3k6","Value":0.0},{"Source":"N6","Destination":"N1","Commodity":"S3T3k6","Value":0.0},{"Source":"N6","Destination":"N2","Commodity":"S3T3k6","Value":0.0},{"Source":"N6","Destination":"N5","Commodity":"S3T3k6","Value":0.0},{"Source":"N6","Destination":"N7","Commodity":"S3T3k6","Value":0.0},{"Source":"N7","Destination":"N2","Commodity":"S3T3k6","Value":0.0},{"Source":"N7","Destination":"N3","Commodity":"S3T3k6","Value":0.0},{"Source":"N7","Destination":"N5","Commodity":"S3T3k6","Value":0.0},{"Source":"N7","Destination":"N6","Commodity":"S3T3k6","Value":0.0},{"Source":"N7","Destination":"N8","Commodity":"S3T3k6","Value":0.0},{"Source":"N8","Destination":"N5","Commodity":"S3T3k6","Value":0.0},{"Source":"N8","Destination":"N7","Commodity":"S3T3k6","Value":0.0},{"Source":"T1","Destination":"T1k1","Commodity":"S3T3k6","Value":0.0},{"Source":"S1","Destination":"T1k1","Commodity":"S3T3k6","Value":0.0},{"Source":"T2","Destination":"T2k2","Commodity":"S3T3k6","Value":0.0},{"Source":"S1","Destination":"T2k2","Commodity":"S3T3k6","Value":0.0},{"Source":"T2","Destination":"T2k3","Commodity":"S3T3k6","Value":0.0},{"Source":"S2","Destination":"T2k3","Commodity":"S3T3k6","Value":0.0},{"Source":"T1","Destination":"T1k4","Commodity":"S3T3k6","Value":0.0},{"Source":"S2","Destination":"T1k4","Commodity":"S3T3k6","Value":0.0},{"Source":"N6","Destination":"T2","Commodity":"S3T3k6","Value":0.0},{"Source":"N7","Destination":"T2","Commodity":"S3T3k6","Value":0.0},{"Source":"N8","Destination":"T2","Commodity":"S3T3k6","Value":0.0},{"Source":"T2","Destination":"T2k4","Commodity":"S3T3k6","Value":0.0},{"Source":"S2","Destination":"T2k4","Commodity":"S3T3k6","Value":0.0},{"Source":"T3","Destination":"T3k4","Commodity":"S3T3k6","Value":0.0},{"Source":"S2","Destination":"T3k4","Commodity":"S3T3k6","Value":0.0},{"Source":"T3","Destination":"T3k5","Commodity":"S3T3k6","Value":0.0},{"Source":"S3","Destination":"T3k5","Commodity":"S3T3k6","Value":0.0},{"Source":"N6","Destination":"T1","Commodity":"S3T3k6","Value":0.0},{"Source":"N7","Destination":"T1","Commodity":"S3T3k6","Value":0.0},{"Source":"T1","Destination":"T1k6","Commodity":"S3T3k6","Value":0.0},{"Source":"S3","Destination":"T1k6","Commodity":"S3T3k6","Value":0.0},{"Source":"N5","Destination":"T3","Commodity":"S3T3k6","Value":1.0},{"Source":"N8","Destination":"T3","Commodity":"S3T3k6","Value":0.0},{"Source":"T3","Destination":"T3k6","Commodity":"S3T3k6","Value":1.0},{"Source":"S3","Destination":"T3k6","Commodity":"S3T3k6","Value":0.0}]}